rdf_summarizer/__init__.py
rdf_summarizer/__main__.py
rdf_summarizer/prefixes.py
rdf_summarizer/summarization.py
rdf_summarizer/trie.py
rdf_summarizer/write_file.py
rdf_summarizer-0.0.2.dist-info/LICENSE
rdf_summarizer-0.0.2.dist-info/METADATA
rdf_summarizer-0.0.2.dist-info/WHEEL
rdf_summarizer-0.0.2.dist-info/entry_points.txt
rdf_summarizer-0.0.2.dist-info/top_level.txt
rdf_summarizer-0.0.2.dist-info/RECORD
