Metadata-Version: 2.1
Name: rdf-summarizer
Version: 0.0.2
Summary: Summarization of a RDF graph
Author-email: Rita Costa <ritasantoscosta9@gmail.com>
License: MIT License        
Project-URL: Homepage, https://github.com/ritasantos11/RDF-Summarizer
Keywords: rdf,summary
Classifier: License :: OSI Approved :: MIT License
Classifier: Programming Language :: Python :: 3
Requires-Python: >=3.9
License-File: LICENSE
Requires-Dist: rdflib
Provides-Extra: dev
Requires-Dist: black ; extra == 'dev'
Requires-Dist: bumpver ; extra == 'dev'
Requires-Dist: isort ; extra == 'dev'
Requires-Dist: pip-tools ; extra == 'dev'
Requires-Dist: pytest ; extra == 'dev'
